Workbook

Sheet Market Data
A1: Oracle Corporation (NYSE: ORCL)
A2: Trading Comparable Companies Analysis — Market Data
A3: Market data as of March 19, 2026 (closing prices)
A4: Source: LSEG Historical Pricing, SEC EDGAR filings, StockAnalysis.com
A6: Market Data & Enterprise Value Build
B7: Ticker | C7: Share Price ($) | D7: Diluted Shares (mm) | E7: Market Cap ($mm) | F7: Total Debt ($mm) | G7: Cash & Equiv. ($mm) | H7: Minority Int. ($mm) | I7: Preferred Eq. ($mm) | J7: Enterprise Value ($mm) | K7: Source Notes
A8: Oracle Corporation | B8: ORCL | C8: 155.52 | D8: 2870 | E8: =C8*D8 -> 446342.4 | F8: 95502 | G8: 10456 | H8: 518 | J8: =E8+F8-G8+IF(H8="",0,H8)+IF(I8="",0,I8) -> 531906.4
A10: Microsoft Corporation | B10: MSFT | C10: 384.67 | D10: 7465 | E10: =C10*D10 -> 2871561.6 | F10: 44000 | G10: 87242 | H10: 1300 | J10: =E10+F10-G10+IF(H10="",0,H10)+IF(I10="",0,I10) -> 2829619.6
A11: SAP SE | B11: SAP | C11: 185.01 | D11: 1220 | E11: =C11*D11 -> 225712.2 | F11: 9860 | G11: 10405 | H11: 600 | J11: =E11+F11-G11+IF(H11="",0,H11)+IF(I11="",0,I11) -> 225767.2
A12: Salesforce, Inc. | B12: CRM | C12: 194.99 | D12: 956 | E12: =C12*D12 -> 186410.44 | F12: 14439 | G12: 9565 | J12: =E12+F12-G12+IF(H12="",0,H12)+IF(I12="",0,I12) -> 191284.44
A13: International Business Machines | B13: IBM | C13: 250.37 | D13: 945 | E13: =C13*D13 -> 236599.65 | F13: 64607 | G13: 14417 | H13: 93 | J13: =E13+F13-G13+IF(H13="",0,H13)+IF(I13="",0,I13) -> 286882.65
A14: ServiceNow, Inc. | B14: NOW | C14: 113.27 | D14: 1047 | E14: =C14*D14 -> 118593.69 | F14: 1500 | G14: 5500 | J14: =E14+F14-G14+IF(H14="",0,H14)+IF(I14="",0,I14) -> 114593.69
A15: Adobe Inc. | B15: ADBE | C15: 245.99 | D15: 427 | E15: =C15*D15 -> 105037.73 | F15: 5700 | G15: 6595 | J15: =E15+F15-G15+IF(H15="",0,H15)+IF(I15="",0,I15) -> 104142.73
A17: Peer Mean | C17: =AVERAGE(C10:C15) -> 229.05 | D17: =AVERAGE(D10:D15) -> 2010 | E17: =AVERAGE(E10:E15) -> 623985.88 | F17: =AVERAGE(F10:F15) -> 23351 | G17: =AVERAGE(G10:G15) -> 22287.333 | H17: =AVERAGE(H10:H15) -> 664.33333 | I17: =IF(COUNT(I10:I15)=0,0,AVERAGE(I10:I15)) -> 0 | J17: =AVERAGE(J10:J15) -> 625381.71
A18: Peer Median | C18: =MEDIAN(C10:C15) -> 220.49 | D18: =MEDIAN(D10:D15) -> 1001.5 | E18: =MEDIAN(E10:E15) -> 206061.32 | F18: =MEDIAN(F10:F15) -> 12149.5 | G18: =MEDIAN(G10:G15) -> 9985 | H18: =MEDIAN(H10:H15) -> 600 | I18: =IF(COUNT(I10:I15)=0,0,MEDIAN(I10:I15)) -> 0 | J18: =MEDIAN(J10:J15) -> 208525.82
A19: Peer High | C19: =MAX(C10:C15) -> 384.67 | D19: =MAX(D10:D15) -> 7465 | E19: =MAX(E10:E15) -> 2871561.6 | F19: =MAX(F10:F15) -> 64607 | G19: =MAX(G10:G15) -> 87242 | H19: =MAX(H10:H15) -> 1300 | I19: =MAX(I10:I15) -> 0 | J19: =MAX(J10:J15) -> 2829619.6
A20: Peer Low | C20: =MIN(C10:C15) -> 113.27 | D20: =MIN(D10:D15) -> 427 | E20: =MIN(E10:E15) -> 105037.73 | F20: =MIN(F10:F15) -> 1500 | G20: =MIN(G10:G15) -> 5500 | H20: =MIN(H10:H15) -> 93 | I20: =MIN(I10:I15) -> 0 | J20: =MIN(J10:J15) -> 104142.73

Sheet Financial Data
A1: Oracle Corporation (NYSE: ORCL)
A2: Trading Comparable Companies Analysis — Financial Metrics
A4: Last Twelve Months Financial Data ($mm)
B5: Ticker | C5: Revenue | D5: Gross Profit | E5: Gross Margin | F5: EBITDA | G5: EBITDA Margin | H5: EBIT | I5: EBIT Margin | J5: Net Income | K5: Oper. Cash Flow | L5: CapEx | M5: Free Cash Flow | N5: FCF Margin | O5: Source
A6: Oracle Corporation | B6: ORCL | C6: 57399 | D6: 40472 | E6: =D6/C6 -> 0.70509939 | F6: 23852 | G6: =F6/C6 -> 0.41554731 | H6: 17678 | I6: =H6/C6 -> 0.30798446 | J6: 12443 | K6: 20800 | L6: -21200 | M6: =K6+L6 -> -400 | N6: =IF(M6=0,"-",M6/C6) -> -0.0069687625
A8: Microsoft Corporation | B8: MSFT | C8: 281724 | D8: 193893 | E8: =D8/C8 -> 0.68823742 | F8: 162681 | G8: =F8/C8 -> 0.57744814 | H8: 128528 | I8: =H8/C8 -> 0.45621956 | J8: 101832 | K8: 136162 | L8: -64551 | M8: =K8+L8 -> 71611 | N8: =IF(M8=0,"-",M8/C8) -> 0.2541885
A9: SAP SE | B9: SAP | C9: 40112 | D9: 29227 | E9: =D9/C9 -> 0.72863482 | F9: 11912 | G9: =F9/C9 -> 0.29696849 | H9: 10483 | I9: =H9/C9 -> 0.26134324 | J9: 7848 | K9: 9265 | L9: -709 | M9: =K9+L9 -> 8556 | N9: =IF(M9=0,"-",M9/C9) -> 0.21330275
A10: Salesforce, Inc. | B10: CRM | C10: 41525 | D10: 32255 | E10: =D10/C10 -> 0.77676099 | F10: 14159 | G10: =F10/C10 -> 0.34097532 | H10: 8331 | I10: =H10/C10 -> 0.20062613 | J10: 7457 | K10: 15000 | L10: -600 | M10: =K10+L10 -> 14400 | N10: =IF(M10=0,"-",M10/C10) -> 0.34677905
A11: International Business Machines | B11: IBM | C11: 67535 | D11: 39297 | E11: =D11/C11 -> 0.58187606 | F11: 16000 | G11: =F11/C11 -> 0.23691419 | H11: 11822 | I11: =H11/C11 -> 0.17504997 | J11: 10570 | K11: 14700 | L11: -1500 | M11: =K11+L11 -> 13200 | N11: =IF(M11=0,"-",M11/C11) -> 0.19545421
A12: ServiceNow, Inc. | B12: NOW | C12: 13278 | D12: 10295 | E12: =D12/C12 -> 0.77534267 | F12: 2562 | G12: =F12/C12 -> 0.19295075 | H12: 1824 | I12: =H12/C12 -> 0.13737009 | J12: 1748 | K12: 5444 | L12: -868 | M12: =K12+L12 -> 4576 | N12: =IF(M12=0,"-",M12/C12) -> 0.34463022
A13: Adobe Inc. | B13: ADBE | C13: 23769 | D13: 21218 | E13: =D13/C13 -> 0.89267533 | F13: 9524 | G13: =F13/C13 -> 0.40068997 | H13: 8706 | I13: =H13/C13 -> 0.3662754 | J13: 7130 | K13: 10030 | L13: -178 | M13: =K13+L13 -> 9852 | N13: =IF(M13=0,"-",M13/C13) -> 0.41448946
A15: Peer Mean | C15: =AVERAGE(C8:C13) -> 77990.5 | D15: =AVERAGE(D8:D13) -> 54364.167 | E15: =AVERAGE(E8:E13) -> 0.74058788 | F15: =AVERAGE(F8:F13) -> 36139.667 | G15: =AVERAGE(G8:G13) -> 0.34099114 | H15: =AVERAGE(H8:H13) -> 28282.333 | I15: =AVERAGE(I8:I13) -> 0.2661474 | J15: =AVERAGE(J8:J13) -> 22764.167 | ... N15: =AVERAGE(N8:N13) -> 0.29480736
A16: Peer Median | C16: =MEDIAN(C8:C13) -> 40818.5 | D16: =MEDIAN(D8:D13) -> 30741 | E16: =MEDIAN(E8:E13) -> 0.75198875 | F16: =MEDIAN(F8:F13) -> 13035.5 | G16: =MEDIAN(G8:G13) -> 0.3189719 | H16: =MEDIAN(H8:H13) -> 9594.5 | I16: =MEDIAN(I8:I13) -> 0.23098468 | J16: =MEDIAN(J8:J13) -> 7652.5 | ... N16: =MEDIAN(N8:N13) -> 0.29940936
A17: Peer High | C17: =MAX(C8:C13) -> 281724 | D17: =MAX(D8:D13) -> 193893 | E17: =MAX(E8:E13) -> 0.89267533 | F17: =MAX(F8:F13) -> 162681 | G17: =MAX(G8:G13) -> 0.57744814 | H17: =MAX(H8:H13) -> 128528 | I17: =MAX(I8:I13) -> 0.45621956 | J17: =MAX(J8:J13) -> 101832 | ... N17: =MAX(N8:N13) -> 0.41448946
A18: Peer Low | C18: =MIN(C8:C13) -> 13278 | D18: =MIN(D8:D13) -> 10295 | E18: =MIN(E8:E13) -> 0.58187606 | F18: =MIN(F8:F13) -> 2562 | G18: =MIN(G8:G13) -> 0.19295075 | H18: =MIN(H8:H13) -> 1824 | I18: =MIN(I8:I13) -> 0.13737009 | J18: =MIN(J8:J13) -> 1748 | ... N18: =MIN(N8:N13) -> 0.19545421
A20: Forward Consensus Estimates
B21: Ticker | C21: FY+1 Rev ($mm) | D21: FY+1 Rev Gr. | E21: FY+2 Rev ($mm) | F21: FY+2 Rev Gr. | G21: FY+1 EPS ($) | H21: FY+2 EPS ($) | I21: LT EPS Gr. | J21: # Analysts
A22: Oracle Corporation | B22: ORCL | C22: 68300 | D22: =C22/'Financial Data'!C6-1 -> 0.1899162 | E22: 88400 | F22: =E22/C22-1 -> 0.2942899 | G22: 7.52 | H22: 8.07 | I22: 0.25 | J22: 47
A24: Microsoft Corporation | B24: MSFT | C24: 334600 | D24: =C24/'Financial Data'!C8-1 -> 0.18768724 | E24: 386700 | F24: =E24/C24-1 -> 0.15570831 | G24: 16.92 | H24: 19.38 | I24: 0.13 | J24: 61
A25: SAP SE | B25: SAP | C25: 44300 | D25: =C25/'Financial Data'!C9-1 -> 0.10440766 | E25: 49600 | F25: =E25/C25-1 -> 0.11963883 | G25: 7.97 | H25: 9.32 | I25: 0.17 | J25: 36
A26: Salesforce, Inc. | B26: CRM | C26: 46000 | D26: =C26/'Financial Data'!C10-1 -> 0.10776641 | E26: 49500 | F26: =E26/C26-1 -> 0.076086957 | G26: 13.15 | H26: 14.66 | I26: 0.12 | J26: 55
A27: International Business Machines | B27: IBM | C27: 71000 | D27: =C27/'Financial Data'!C11-1 -> 0.05130673 | E27: 75000 | F27: =E27/C27-1 -> 0.056338028 | G27: 12.51 | H27: 13.57 | I27: 0.08 | J27: 24
A28: ServiceNow, Inc. | B28: NOW | C28: 16000 | D28: =C28/'Financial Data'!C12-1 -> 0.20500075 | E28: 20000 | F28: =E28/C28-1 -> 0.25 | G28: 4.19 | H28: 5.56 | I28: 0.22 | J28: 49
A29: Adobe Inc. | B29: ADBE | C29: 26000 | D29: =C29/'Financial Data'!C13-1 -> 0.093861753 | E29: 28500 | F29: =E29/C29-1 -> 0.096153846 | G29: 23.4 | H29: 26.5 | I29: 0.11 | J29: 36
A31: Peer Mean | C31: =AVERAGE(C24:C29) -> 89650 | D31: =AVERAGE(D24:D29) -> 0.12500509 | E31: =AVERAGE(E24:E29) -> 101550 | F31: =AVERAGE(F24:F29) -> 0.12565433 | G31: =AVERAGE(G24:G29) -> 13.023333 | H31: =AVERAGE(H24:H29) -> 14.831667 | I31: =AVERAGE(I24:I29) -> 0.13833333 | J31: =AVERAGE(J24:J29) -> 43.5
A32: Peer Median | C32: =MEDIAN(C24:C29) -> 45150 | D32: =MEDIAN(D24:D29) -> 0.10608703 | E32: =MEDIAN(E24:E29) -> 49550 | F32: =MEDIAN(F24:F29) -> 0.10789634 | G32: =MEDIAN(G24:G29) -> 12.83 | H32: =MEDIAN(H24:H29) -> 14.115 | I32: =MEDIAN(I24:I29) -> 0.125 | J32: =MEDIAN(J24:J29) -> 42.5
A35: Growth & Profitability Benchmarking
B36: Ticker | C36: 3-Yr Rev CAGR | D36: 3-Yr EBITDA CAGR | E36: ROIC | F36: ROA | G36: Net Debt/EBITDA | H36: Interest Cov. | I36: Employees | J36: Rev/Employee ($K)
A37: Oracle Corporation | B37: ORCL | C37: 0.106 | D37: 0.193 | E37: 0.147 | F37: 0.074 | G37: =('Market Data'!F8-'Market Data'!G8)/'Financial Data'!F6 -> 3.565571 | H37: ='Financial Data'!F6/3578 -> 6.666294 | I37: 162000 | J37: ='Financial Data'!C6/I37*1000 -> 354.31481
A39: Microsoft Corporation | B39: MSFT | C39: 0.125 | D39: 0.185 | E39: 0.351 | F39: 0.165 | G39: =('Market Data'!F10-'Market Data'!G10)/'Financial Data'!F8 -> -0.26580855 | H39: ='Financial Data'!F8/2700 -> 60.252222 | I39: 228000 | J39: ='Financial Data'!C8/I39*1000 -> 1235.6316
A40: SAP SE | B40: SAP | C40: 0.06 | D40: 0.205 | E40: 0.159 | F40: 0.11 | G40: =('Market Data'!F11-'Market Data'!G11)/'Financial Data'!F9 -> -0.045752183 | H40: ='Financial Data'!F9/1036 -> 11.498069 | I40: 110000 | J40: ='Financial Data'!C9/I40*1000 -> 364.65455
A41: Salesforce, Inc. | B41: CRM | C41: 0.098 | D41: 0.297 | E41: 0.102 | F41: 0.066 | G41: =('Market Data'!F12-'Market Data'!G12)/'Financial Data'!F10 -> 0.34423335 | H41: ='Financial Data'!F10/330 -> 42.906061 | I41: 83334 | J41: ='Financial Data'!C10/I41*1000 -> 498.29601
A42: International Business Machines | B42: IBM | C42: 0.037 | D42: 0.072 | E42: 0.121 | F42: 0.07 | G42: =('Market Data'!F13-'Market Data'!G13)/'Financial Data'!F11 -> 3.136875 | H42: ='Financial Data'!F11/1900 -> 8.4210526 | I42: 270300 | J42: ='Financial Data'!C11/I42*1000 -> 249.85202
A43: ServiceNow, Inc. | B43: NOW | C43: 0.224 | D43: 0.468 | E43: 0.32 | F43: 0.083 | G43: =('Market Data'!F14-'Market Data'!G14)/'Financial Data'!F12 -> -1.5612802 | H43: ='Financial Data'!F12/24 -> 106.75 | I43: 23000 | J43: ='Financial Data'!C12/I43*1000 -> 577.30435
A44: Adobe Inc. | B44: ADBE | C44: 0.105 | D44: 0.111 | E44: 0.504 | F44: 0.242 | G44: =('Market Data'!F15-'Market Data'!G15)/'Financial Data'!F13 -> -0.093973121 | H44: ='Financial Data'!F13/263 -> 36.212928 | I44: 31360 | J44: ='Financial Data'!C13/I44*1000 -> 757.94005
A46: Peer Mean | C46: =AVERAGE(C39:C44) -> 0.10816667 | D46: =AVERAGE(D39:D44) -> 0.223 | E46: =AVERAGE(E39:E44) -> 0.2595 | F46: =AVERAGE(F39:F44) -> 0.12266667 | G46: =AVERAGE(G39:G44) -> 0.25238238 | H46: =AVERAGE(H39:H44) -> 44.340055 | I46: =AVERAGE(I39:I44) -> 124332.33 | J46: =AVERAGE(J39:J44) -> 613.94643
A47: Peer Median | C47: =MEDIAN(C39:C44) -> 0.1015 | D47: =MEDIAN(D39:D44) -> 0.195 | E47: =MEDIAN(E39:E44) -> 0.2395 | F47: =MEDIAN(F39:F44) -> 0.0965 | G47: =MEDIAN(G39:G44) -> -0.069862652 | H47: =MEDIAN(H39:H44) -> 39.559494 | I47: =MEDIAN(I39:I44) -> 96667 | J47: =MEDIAN(J39:J44) -> 537.80018

Sheet Valuation Multiples
A1: Oracle Corporation (NYSE: ORCL)
A2: Trading Comparable Companies Analysis — Valuation Multiples
A4: Last Twelve Months Valuation Multiples
B5: Ticker | C5: EV / Rev | D5: EV / GP | E5: EV / EBITDA | F5: EV / EBIT | G5: P / E | H5: P / FCF | I5: FCF Yield
A6: Oracle Corporation | B6: ORCL | C6: ='Market Data'!J8/'Financial Data'!C6 -> 9.2668235 | D6: ='Market Data'!J8/'Financial Data'!D6 -> 13.142578 | E6: ='Market Data'!J8/'Financial Data'!F6 -> 22.300285 | F6: ='Market Data'!J8/'Financial Data'!H6 -> 30.088607 | G6: ='Market Data'!E8/'Financial Data'!J6 -> 35.870964 | H6: N/M | I6: ='Financial Data'!M6/'Market Data'!E8 -> -0.00089617298
A8: Microsoft Corporation | B8: MSFT | C8: ='Market Data'!J10/'Financial Data'!C8 -> 10.043942 | D8: ='Market Data'!J10/'Financial Data'!D8 -> 14.593717 | E8: ='Market Data'!J10/'Financial Data'!F8 -> 17.39367 | F8: ='Market Data'!J10/'Financial Data'!H8 -> 22.015588 | G8: ='Market Data'!E10/'Financial Data'!J8 -> 28.19901 | H8: ='Market Data'!E10/'Financial Data'!M8 -> 40.099448 | I8: ='Financial Data'!M8/'Market Data'!E10 -> 0.024937999
A9: SAP SE | B9: SAP | C9: ='Market Data'!J11/'Financial Data'!C9 -> 5.6284204 | D9: ='Market Data'!J11/'Financial Data'!D9 -> 7.7246108 | E9: ='Market Data'!J11/'Financial Data'!F9 -> 18.952921 | F9: ='Market Data'!J11/'Financial Data'!H9 -> 21.536507 | G9: ='Market Data'!E11/'Financial Data'!J9 -> 28.760474 | H9: ='Market Data'!E11/'Financial Data'!M9 -> 26.380575 | I9: ='Financial Data'!M9/'Market Data'!E11 -> 0.037906679
A10: Salesforce, Inc. | B10: CRM | C10: ='Market Data'!J12/'Financial Data'!C10 -> 4.6064886 | D10: ='Market Data'!J12/'Financial Data'!D10 -> 5.930381 | E10: ='Market Data'!J12/'Financial Data'!F10 -> 13.509742 | F10: ='Market Data'!J12/'Financial Data'!H10 -> 22.960562 | G10: ='Market Data'!E12/'Financial Data'!J10 -> 24.998047 | H10: ='Market Data'!E12/'Financial Data'!M10 -> 12.945169 | I10: ='Financial Data'!M10/'Market Data'!E12 -> 0.077248892
A11: International Business Machines | B11: IBM | C11: ='Market Data'!J13/'Financial Data'!C11 -> 4.2479107 | D11: ='Market Data'!J13/'Financial Data'!D11 -> 7.3003703 | E11: ='Market Data'!J13/'Financial Data'!F11 -> 17.930166 | F11: ='Market Data'!J13/'Financial Data'!H11 -> 24.266846 | G11: ='Market Data'!E13/'Financial Data'!J11 -> 22.384073 | H11: ='Market Data'!E13/'Financial Data'!M11 -> 17.924216 | I11: ='Financial Data'!M11/'Market Data'!E13 -> 0.055790446
A12: ServiceNow, Inc. | B12: NOW | C12: ='Market Data'!J14/'Financial Data'!C12 -> 8.6303427 | D12: ='Market Data'!J14/'Financial Data'!D12 -> 11.131004 | E12: ='Market Data'!J14/'Financial Data'!F12 -> 44.728216 | F12: ='Market Data'!J14/'Financial Data'!H12 -> 62.825488 | G12: ='Market Data'!E14/'Financial Data'!J12 -> 67.84536 | H12: ='Market Data'!E14/'Financial Data'!M12 -> 25.916453 | I12: ='Financial Data'!M12/'Market Data'!E14 -> 0.038585527
A13: Adobe Inc. | B13: ADBE | C13: ='Market Data'!J15/'Financial Data'!C13 -> 4.3814519 | D13: ='Market Data'!J15/'Financial Data'!D13 -> 4.9082256 | E13: ='Market Data'!J15/'Financial Data'!F13 -> 10.934768 | F13: ='Market Data'!J15/'Financial Data'!H13 -> 11.962179 | G13: ='Market Data'!E15/'Financial Data'!J13 -> 14.731799 | H13: ='Market Data'!E15/'Financial Data'!M13 -> 10.661564 | I13: ='Financial Data'!M13/'Market Data'!E15 -> 0.093794868
A15: Peer Mean | C15: =AVERAGE(C8:C13) -> 6.2564261 | D15: =AVERAGE(D8:D13) -> 8.5980515 | E15: =AVERAGE(E8:E13) -> 20.574914 | F15: =AVERAGE(F8:F13) -> 27.594528 | G15: =AVERAGE(G8:G13) -> 31.153127 | H15: =AVERAGE(H8:H13) -> 22.321238 | I15: =AVERAGE(I8:I13) -> 0.054710735
A16: Peer Median | C16: =MEDIAN(C8:C13) -> 5.1174545 | D16: =MEDIAN(D8:D13) -> 7.5124905 | E16: =MEDIAN(E8:E13) -> 17.661918 | F16: =MEDIAN(F8:F13) -> 22.488075 | G16: =MEDIAN(G8:G13) -> 26.598529 | H16: =MEDIAN(H8:H13) -> 21.920335 | I16: =MEDIAN(I8:I13) -> 0.047187986
A17: Peer High | C17: =MAX(C8:C13) -> 10.043942 | D17: =MAX(D8:D13) -> 14.593717 | E17: =MAX(E8:E13) -> 44.728216 | F17: =MAX(F8:F13) -> 62.825488 | G17: =MAX(G8:G13) -> 67.84536 | H17: =MAX(H8:H13) -> 40.099448 | I17: =MAX(I8:I13) -> 0.093794868
A18: Peer Low | C18: =MIN(C8:C13) -> 4.2479107 | D18: =MIN(D8:D13) -> 4.9082256 | E18: =MIN(E8:E13) -> 10.934768 | F18: =MIN(F8:F13) -> 11.962179 | G18: =MIN(G8:G13) -> 14.731799 | H18: =MIN(H8:H13) -> 10.661564 | I18: =MIN(I8:I13) -> 0.024937999
A19: Oracle Premium / (Discount) to Peer Median | C19: =(C6/C16)-1 -> 0.81082674 | D19: =(D6/D16)-1 -> 0.74943017 | E19: =(E6/E16)-1 -> 0.2626197 | F19: =(F6/F16)-1 -> 0.33798056 | G19: =(G6/G16)-1 -> 0.34860707 | H19: N/M | I19: =(I6/I16)-1 -> -1.0189915
A22: Forward (Next Twelve Months) Valuation Multiples
B23: Ticker | C23: NTM EV/Rev | D23: NTM EV/EBITDA | E23: NTM P/E | F23: PEG Ratio
A24: Oracle Corporation | B24: ORCL | C24: ='Market Data'!J8/'Financial Data'!C22 -> 7.787795 | D24: ='Market Data'!J8/('Financial Data'!C22*'Financial Data'!G6) -> 18.741055 | E24: ='Market Data'!C8/'Financial Data'!G22 -> 20.680851 | F24: =IF('Financial Data'!I22=0,"N/M",(E24)/('Financial Data'!I22*100)) -> 0.82723404
A26: Microsoft Corporation | B26: MSFT | C26: ='Market Data'!J10/'Financial Data'!C24 -> 8.4567231 | D26: ='Market Data'!J10/('Financial Data'!C24*'Financial Data'!G8) -> 14.644991 | E26: ='Market Data'!C10/'Financial Data'!G24 -> 22.734634 | F26: =IF('Financial Data'!I24=0,"N/M",(E26)/('Financial Data'!I24*100)) -> 1.748818
A27: SAP SE | B27: SAP | C27: ='Market Data'!J11/'Financial Data'!C25 -> 5.0963251 | D27: ='Market Data'!J11/('Financial Data'!C25*'Financial Data'!G9) -> 17.161164 | E27: ='Market Data'!C11/'Financial Data'!G25 -> 23.2133 | F27: =IF('Financial Data'!I25=0,"N/M",(E27)/('Financial Data'!I25*100)) -> 1.3654882
A28: Salesforce, Inc. | B28: CRM | C28: ='Market Data'!J12/'Financial Data'!C26 -> 4.1583574 | D28: ='Market Data'!J12/('Financial Data'!C26*'Financial Data'!G10) -> 12.195479 | E28: ='Market Data'!C12/'Financial Data'!G26 -> 14.828137 | F28: =IF('Financial Data'!I26=0,"N/M",(E28)/('Financial Data'!I26*100)) -> 1.2356781
A29: International Business Machines | B29: IBM | C29: ='Market Data'!J13/'Financial Data'!C27 -> 4.0406007 | D29: ='Market Data'!J13/('Financial Data'!C27*'Financial Data'!G11) -> 17.055123 | E29: ='Market Data'!C13/'Financial Data'!G27 -> 20.013589 | F29: =IF('Financial Data'!I27=0,"N/M",(E29)/('Financial Data'!I27*100)) -> 2.5016986
A30: ServiceNow, Inc. | B30: NOW | C30: ='Market Data'!J14/'Financial Data'!C28 -> 7.1621056 | D30: ='Market Data'!J14/('Financial Data'!C28*'Financial Data'!G12) -> 37.118828 | E30: ='Market Data'!C14/'Financial Data'!G28 -> 27.033413 | F30: =IF('Financial Data'!I28=0,"N/M",(E30)/('Financial Data'!I28*100)) -> 1.2287915
A31: Adobe Inc. | B31: ADBE | C31: ='Market Data'!J15/'Financial Data'!C29 -> 4.0054896 | D31: ='Market Data'!J15/('Financial Data'!C29*'Financial Data'!G13) -> 9.9964808 | E31: ='Market Data'!C15/'Financial Data'!G29 -> 10.512393 | F31: =IF('Financial Data'!I29=0,"N/M",(E31)/('Financial Data'!I29*100)) -> 0.95567211
A33: Peer Mean | C33: =AVERAGE(C26:C31) -> 5.4866002 | D33: =AVERAGE(D26:D31) -> 18.028678 | E33: =AVERAGE(E26:E31) -> 19.722578 | F33: =AVERAGE(F26:F31) -> 1.5060244
A34: Peer Median | C34: =MEDIAN(C26:C31) -> 4.6273412 | D34: =MEDIAN(D26:D31) -> 15.850057 | E34: =MEDIAN(E26:E31) -> 21.374111 | F34: =MEDIAN(F26:F31) -> 1.3005832
A35: Peer High | C35: =MAX(C26:C31) -> 8.4567231 | D35: =MAX(D26:D31) -> 37.118828 | E35: =MAX(E26:E31) -> 27.033413 | F35: =MAX(F26:F31) -> 2.5016986
A36: Peer Low | C36: =MIN(C26:C31) -> 4.0054896 | D36: =MIN(D26:D31) -> 9.9964808 | E36: =MIN(E26:E31) -> 10.512393 | F36: =MIN(F26:F31) -> 0.95567211
A37: Oracle Premium / (Discount) to Peer Median | C37: =(C24/C34)-1 -> 0.68299562 | D37: =(D24/D34)-1 -> 0.18239668 | E37: =(E24/E34)-1 -> -0.032434578 | F37: =(F24/F34)-1 -> -0.36395144

Sheet Implied Valuation
A1: Oracle Corporation (NYSE: ORCL)
A2: Comparable Companies Implied Valuation Range
A4: Implied Enterprise Value from Peer Multiples ($mm)
A5: Methodology | B5: Low (25th Pctl) | C5: Median | D5: High (75th Pctl) | E5: Mean | F5: Notes
A6: LTM EV / Revenue | B6: =QUARTILE('Valuation Multiples'!C8:C13,1)*'Financial Data'!C6 -> 254720.18 | C6: =MEDIAN('Valuation Multiples'!C8:C13)*'Financial Data'!C6 -> 293736.77 | D6: =QUARTILE('Valuation Multiples'!C8:C13,3)*'Financial Data'!C6 -> 452296.21 | E6: =AVERAGE('Valuation Multiples'!C8:C13)*'Financial Data'!C6 -> 359112.6
A7: LTM EV / EBITDA | B7: =QUARTILE('Valuation Multiples'!E8:E13,1)*'Financial Data'!F6 -> 345394.23 | C7: =MEDIAN('Valuation Multiples'!E8:E13)*'Financial Data'!F6 -> 421272.06 | D7: =QUARTILE('Valuation Multiples'!E8:E13,3)*'Financial Data'!F6 -> 445966.39 | E7: =AVERAGE('Valuation Multiples'!E8:E13)*'Financial Data'!F6 -> 490752.84
A8: LTM EV / EBIT | B8: =QUARTILE('Valuation Multiples'!F8:F13,1)*'Financial Data'!H6 -> 382839.67 | C8: =MEDIAN('Valuation Multiples'!F8:F13)*'Financial Data'!H6 -> 397544.19 | D8: =QUARTILE('Valuation Multiples'!F8:F13,3)*'Financial Data'!H6 -> 423216.18 | E8: =AVERAGE('Valuation Multiples'!F8:F13)*'Financial Data'!H6 -> 487816.07
A9: NTM EV / Revenue | B9: =QUARTILE('Valuation Multiples'!C26:C31,1)*'Financial Data'!C22 -> 277983.72 | C9: =MEDIAN('Valuation Multiples'!C26:C31)*'Financial Data'!C22 -> 316047.41 | D9: =QUARTILE('Valuation Multiples'!C26:C31,3)*'Financial Data'!C22 -> 453898.61 | E9: =AVERAGE('Valuation Multiples'!C26:C31)*'Financial Data'!C22 -> 374734.8
A10: NTM EV / EBITDA | B10: =QUARTILE('Valuation Multiples'!D26:D31,1)*('Financial Data'!C22*'Financial Data'!G6) -> 363511.08 | C10: =MEDIAN('Valuation Multiples'!D26:D31)*('Financial Data'!C22*'Financial Data'!G6) -> 449854.44 | D10: =QUARTILE('Valuation Multiples'!D26:D31,3)*('Financial Data'!C22*'Financial Data'!G6) -> 486313.72 | E10: =AVERAGE('Valuation Multiples'!D26:D31)*('Financial Data'!C22*'Financial Data'!G6) -> 511687.79
A13: Enterprise Value to Equity Value Bridge
A14: Selected Implied Enterprise Value — Low ($mm)
A15: Selected Implied Enterprise Value — Base ($mm)
A16: Selected Implied Enterprise Value — High ($mm)
A18: Less: Total Debt ($mm) | B18: ='Market Data'!F8 -> 95502
A19: Less: Minority Interest ($mm) | B19: ='Market Data'!H8 -> 518
A20: Plus: Cash and Cash Equivalents ($mm) | B20: ='Market Data'!G8 -> 10456
A22: Implied Equity Value — Low ($mm) | B22: =B14-B18-B19+B20 -> -85564
A23: Implied Equity Value — Base ($mm) | B23: =B15-B18-B19+B20 -> -85564
A24: Implied Equity Value — High ($mm) | B24: =B16-B18-B19+B20 -> -85564
A26: Diluted Shares Outstanding (millions) | B26: ='Market Data'!D8 -> 2870
A28: Implied Share Price — Low ($) | B28: =IF(B22="","",B22/B26) -> -29.81324
A29: Implied Share Price — Base ($) | B29: =IF(B23="","",B23/B26) -> -29.81324
A30: Implied Share Price — High ($) | B30: =IF(B24="","",B24/B26) -> -29.81324
A32: Current Share Price ($) | B32: ='Market Data'!C8 -> 155.52
A33: Implied Upside / (Downside) — Low (%) | B33: =IF(B28="","",B28/B32-1) -> -1.1917004
A34: Implied Upside / (Downside) — Base (%) | B34: =IF(B29="","",B29/B32-1) -> -1.1917004
A35: Implied Upside / (Downside) — High (%) | B35: =IF(B30="","",B30/B32-1) -> -1.1917004
A38: Peer Tier Mapping
A39: Company | B39: Tier | C39: Rationale
A40: Microsoft Corporation | B40: Tier 1 — Cloud & Enterprise | C40: Cloud infrastructure + enterprise applications overlap
A41: SAP SE | B41: Tier 1 — Enterprise Applications | C41: Direct Enterprise Resource Planning competitor
A42: Salesforce, Inc. | B42: Tier 1 — Cloud Applications | C42: Cloud Software as a Service overlap
A43: International Business Machines | B43: Tier 2 — Legacy Enterprise | C43: Legacy infrastructure + consulting; lower growth
A44: ServiceNow, Inc. | B44: Tier 2 — Cloud Pure-Play | C44: Cloud-only; limited infrastructure overlap
A45: Adobe Inc. | B45: Tier 2 — Cloud Applications | C45: Cloud Software as a Service; different end markets
A48: Beta & Weighted Average Cost of Capital Inputs
B49: ORCL | C49: MSFT | D49: SAP | E49: CRM | F49: IBM | G49: NOW | H49: ADBE
A50: Beta (5-Year Monthly vs. S&P 500) | B50: 1.65 | C50: 1.08 | D50: 0.84 | E50: 1.31 | F50: 0.69 | G50: 1.02 | H50: 1.52
A51: Fiscal Year End | B51: May 31 | C51: June 30 | D51: December 31 | E51: January 31 | F51: December 31 | G51: December 31 | H51: ~November 30
